LMS/__init__.py
LMS/client.py
LMS/server.py
lms_python-1.0.3.dist-info/licenses/licenses.json
lms_python-1.0.3.dist-info/METADATA
lms_python-1.0.3.dist-info/WHEEL
lms_python-1.0.3.dist-info/top_level.txt
lms_python-1.0.3.dist-info/RECORD
